ansi_interactive_search/__init__.py
ansi_interactive_search/console.py
ansi_interactive_search/examples.py
ansi_interactive_search-0.0.2.dist-info/METADATA
ansi_interactive_search-0.0.2.dist-info/RECORD
ansi_interactive_search-0.0.2.dist-info/WHEEL
ansi_interactive_search-0.0.2.dist-info/top_level.txt
