Metadata-Version: 2.1
Name: ansi-interactive-search
Version: 0.0.2
Summary: Ansi based interactive search UI
Home-page: https://github.com/masterginger/py-ansi-interactive-search
Author: Bian Jiang
Author-email: incomingemail2016@gmail.com
License: UNKNOWN
Platform: UNKNOWN
Classifier: Development Status :: 4 - Beta
Classifier: Environment :: Console
Classifier: License :: OSI Approved :: MIT License
Classifier: Operating System :: MacOS :: MacOS X
Classifier: Programming Language :: Python :: 2.7
Classifier: Topic :: Desktop Environment
Requires-Dist: unbuffered-input
